dlmscrypto/dlms_crypto_tool/__init__.py
dlmscrypto/dlms_crypto_tool/cli.py
dlmscrypto/dlms_crypto_tool/dlms_crypto.py
dlmscrypto/tests/__init__.py
dlmscrypto/tests/test_dlms_crypto.py
dlms_crypto_tool-0.0.1.dist-info/METADATA
dlms_crypto_tool-0.0.1.dist-info/WHEEL
dlms_crypto_tool-0.0.1.dist-info/entry_points.txt
dlms_crypto_tool-0.0.1.dist-info/top_level.txt
dlms_crypto_tool-0.0.1.dist-info/RECORD
