Metadata-Version: 2.4
Name: dlms_crypto_tool
Version: 0.0.1
Summary: A tool for encrypting, decrypting, and authenticating DLMS APDU messages.
Author-email: ricgeek <solidkind@gmail.com>
Requires-Python: >=3.6
Requires-Dist: cryptography
